promptxml/__init__.py
promptxml/item.py
promptxml/section.py
promptxml-0.1.1.dist-info/LICENSE
promptxml-0.1.1.dist-info/METADATA
promptxml-0.1.1.dist-info/WHEEL
promptxml-0.1.1.dist-info/RECORD
