Metadata-Version: 2.1
Name: promptxml
Version: 0.1.1
Summary: A tool designed to create prompt instructions for neural networks in XML format.
Home-page: https://github.com/barabum0/promptxml
License: MIT
Keywords: python,chatgpt,ai,prompt,xml,instruction
Author: sushka
Author-email: r.m.poltorabatko@gmail.com
Requires-Python: >=3.12,<4.0
Classifier: Intended Audience :: Developers
Classifier: License :: OSI Approved :: MIT License
Classifier: Operating System :: OS Independent
Classifier: Programming Language :: Python
Classifier: Programming Language :: Python :: 3
Classifier: Programming Language :: Python :: 3.12
Classifier: Topic :: Software Development :: Libraries :: Python Modules
Project-URL: Repository, https://github.com/barabum0/promptxml
